sandu/__init__.py
sandu/gaussian_process_emulator.py
sandu/data_types/__init__.py
sandu/data_types/sensitivity_input.py
sandu/data_types/uncertainty_input.py
sandu/sensitivity_analysis/__init__.py
sandu/sensitivity_analysis/cluster_based.py
sandu/sensitivity_analysis/sobol.py
sandu/uncertainty_quantification/__init__.py
sandu/uncertainty_quantification/confidence_intervals.py
sandu/uncertainty_quantification/mean_time_series.py
sandu-0.1.4.dist-info/LICENSE.txt.txt
sandu-0.1.4.dist-info/METADATA
sandu-0.1.4.dist-info/WHEEL
sandu-0.1.4.dist-info/top_level.txt
sandu-0.1.4.dist-info/RECORD
