Metadata-Version: 2.1
Name: sandu
Version: 0.1.4
Summary: High Level Sensitivity and Uncertainty (SandU) Analysis Tools.
Home-page: https://github.com/ErikRZH/sandu
Author: Erik Rydow
Author-email: erik.rydow@eng.ox.ac
License: UNKNOWN
Keywords: sensitivity-analysis,ensemble-analysis,uncertainty-analysis,uncertainty-quantification,analysis-of-mathematical-models
Platform: UNKNOWN
Classifier: Development Status :: 3 - Alpha
Classifier: Intended Audience :: Science/Research
Classifier: Topic :: Software Development :: Build Tools
Classifier: License :: OSI Approved :: MIT License
Classifier: Programming Language :: Python :: 3.8
Requires-Python: >=3.6, <4
License-File: LICENSE.txt.txt
Requires-Dist: numpy
Requires-Dist: pandas
Requires-Dist: sklearn
Requires-Dist: SALib
Requires-Dist: matplotlib (>=3.5)
Requires-Dist: tslearn
Requires-Dist: ujson
